{
  "sections": {
    "main": {
      "type": "main-product",
      "blocks": {
        "vendor": {
          "type": "text",
          "settings": {
            "text": "{{ product.vendor }}",
            "text_style": "uppercase"
          }
        },
        "title": {
          "type": "title",
          "settings": {
          }
        },
        "caption": {
          "type": "text",
          "settings": {
            "text": "{{ product.metafields.descriptors.subtitle.value }}",
            "text_style": "subtitle"
          }
        },
        "price": {
          "type": "price",
          "settings": {
          }
        },
        "variant_picker": {
          "type": "variant_picker",
          "settings": {
            "picker_type": "button",
            "swatch_shape": "circle"
          }
        },
        "quantity_selector": {
          "type": "quantity_selector",
          "settings": {
          }
        },
        "buy_buttons": {
          "type": "buy_buttons",
          "settings": {
            "show_dynamic_checkout": true,
            "show_gift_card_recipient": true
          }
        },
        "description": {
          "type": "description",
          "settings": {
          }
        },
        "collapsible-row-0": {
          "type": "collapsible_tab",
          "settings": {
            "heading": "Materials",
            "icon": "leather",
            "content": "",
            "page": ""
          }
        },
        "collapsible-row-1": {
          "type": "collapsible_tab",
          "settings": {
            "heading": "Shipping & Returns",
            "icon": "truck",
            "content": "",
            "page": ""
          }
        },
        "collapsible-row-2": {
          "type": "collapsible_tab",
          "settings": {
            "heading": "Dimensions",
            "icon": "ruler",
            "content": "",
            "page": ""
          }
        },
        "collapsible-row-3": {
          "type": "collapsible_tab",
          "settings": {
            "heading": "Care Instructions",
            "icon": "heart",
            "content": "",
            "page": ""
          }
        },
        "share": {
          "type": "share",
          "settings": {
            "share_label": "Share"
          }
        }
      },
      "block_order": [
        "vendor",
        "title",
        "caption",
        "price",
        "variant_picker",
        "quantity_selector",
        "buy_buttons",
        "description",
        "collapsible-row-0",
        "collapsible-row-1",
        "collapsible-row-2",
        "collapsible-row-3",
        "share"
      ],
      "settings": {
        "enable_sticky_info": true,
        "color_scheme": "",
        "media_size": "medium",
        "constrain_to_viewport": true,
        "media_fit": "contain",
        "gallery_layout": "stacked",
        "media_position": "left",
        "image_zoom": "hover",
        "mobile_thumbnails": "show",
        "hide_variants": true,
        "enable_video_looping": false,
        "padding_top": 36,
        "padding_bottom": 12
      }
    },
    "features_carousel_RgGmn3": {
      "type": "features-carousel",
      "blocks": {
        "slide_F6TMMx": {
          "type": "slide",
          "settings": {
            "image": "shopify:\/\/shop_images\/slide1-664cffdd1394a.webp"
          }
        },
        "slide_RgUgNP": {
          "type": "slide",
          "settings": {
            "image": "shopify:\/\/shop_images\/slide2-664cffe273a2f.webp"
          }
        },
        "slide_WWdqL3": {
          "type": "slide",
          "settings": {
            "image": "shopify:\/\/shop_images\/slide3-664cffeb3cf5a.webp"
          }
        },
        "feature_9hjELX": {
          "type": "feature",
          "settings": {
            "icon": "cucumber",
            "heading": "",
            "description": ""
          }
        },
        "feature_DTpaGX": {
          "type": "feature",
          "settings": {
            "icon": "cucumber",
            "heading": "",
            "description": ""
          }
        },
        "feature_JEmjQB": {
          "type": "feature",
          "settings": {
            "icon": "cucumber",
            "heading": "",
            "description": ""
          }
        },
        "feature_bFmTam": {
          "type": "feature",
          "settings": {
            "icon": "cucumber",
            "heading": "",
            "description": ""
          }
        },
        "feature_BJdnA6": {
          "type": "feature",
          "settings": {
            "icon": "cucumber",
            "heading": "",
            "description": ""
          }
        },
        "feature_GRLjA4": {
          "type": "feature",
          "settings": {
            "icon": "cucumber",
            "heading": "",
            "description": ""
          }
        }
      },
      "block_order": [
        "slide_F6TMMx",
        "slide_RgUgNP",
        "slide_WWdqL3",
        "feature_9hjELX",
        "feature_DTpaGX",
        "feature_JEmjQB",
        "feature_bFmTam",
        "feature_BJdnA6",
        "feature_GRLjA4"
      ],
      "settings": {
        "title": "Featured carousel",
        "heading_color": "#fff",
        "padding_top": 36,
        "padding_bottom": 36
      }
    },
    "brand_section_bJpXhd": {
      "type": "brand-section",
      "blocks": {
        "brand_raN4jR": {
          "type": "brand",
          "settings": {
            "image": "shopify:\/\/shop_images\/womens-health-logo-664c66cad40ba.webp",
            "description": "",
            "color": "#0E1B4D"
          }
        },
        "brand_HcyDYJ": {
          "type": "brand",
          "settings": {
            "image": "shopify:\/\/shop_images\/logo-attbmn5hwo6j64dte-664c66cbbf780.webp",
            "description": "",
            "color": "#0E1B4D"
          }
        },
        "brand_TjGHMU": {
          "type": "brand",
          "settings": {
            "image": "shopify:\/\/shop_images\/business-insider-664c66cc14c1a.webp",
            "description": "",
            "color": "#0E1B4D"
          }
        },
        "brand_K6JGFm": {
          "type": "brand",
          "settings": {
            "image": "shopify:\/\/shop_images\/the-times-masthead-664c66cd575c5.webp",
            "description": "",
            "color": "#0E1B4D"
          }
        }
      },
      "block_order": [
        "brand_raN4jR",
        "brand_HcyDYJ",
        "brand_TjGHMU",
        "brand_K6JGFm"
      ],
      "settings": {
        "background": "#d7f1f6",
        "heading": "As <strong>seen<\/strong> in",
        "heading_color": "#0e1b4d"
      }
    },
    "multicolumn": {
      "type": "multicolumn",
      "blocks": {
        "column_pBUXz8": {
          "type": "column",
          "settings": {
            "icon": "science",
            "title": "Column",
            "text": "",
            "link_label": "",
            "link": ""
          }
        },
        "column_KwQ3mn": {
          "type": "column",
          "settings": {
            "icon": "science",
            "title": "Column",
            "text": "",
            "link_label": "",
            "link": ""
          }
        },
        "column_gLBaQe": {
          "type": "column",
          "settings": {
            "icon": "science",
            "title": "Column",
            "text": "",
            "link_label": "",
            "link": ""
          }
        },
        "column_Q643zP": {
          "type": "column",
          "settings": {
            "icon": "science",
            "title": "Column",
            "text": "",
            "link_label": "",
            "link": ""
          }
        },
        "column_UhVhT4": {
          "type": "column",
          "settings": {
            "icon": "science",
            "title": "Column",
            "text": "",
            "link_label": "",
            "link": ""
          }
        },
        "column_QEAFnU": {
          "type": "column",
          "settings": {
            "icon": "science",
            "title": "Column",
            "text": "",
            "link_label": "",
            "link": ""
          }
        }
      },
      "block_order": [
        "column_pBUXz8",
        "column_KwQ3mn",
        "column_gLBaQe",
        "column_Q643zP",
        "column_UhVhT4",
        "column_QEAFnU"
      ],
      "settings": {
        "title": "",
        "heading_size": "h1",
        "image_width": "full",
        "image_ratio": "adapt",
        "columns_desktop": 2,
        "column_alignment": "left",
        "background_style": "none",
        "button_label": "",
        "button_link": "",
        "color_scheme": "scheme-1",
        "columns_mobile": "1",
        "swipe_on_mobile": false,
        "padding_top": 36,
        "padding_bottom": 36
      }
    },
    "related-products": {
      "type": "related-products",
      "settings": {
        "heading": "You may also like",
        "heading_size": "h2",
        "products_to_show": 4,
        "columns_desktop": 4,
        "color_scheme": "scheme-1",
        "image_ratio": "square",
        "image_shape": "default",
        "show_secondary_image": true,
        "show_vendor": false,
        "show_rating": false,
        "columns_mobile": "2",
        "padding_top": 36,
        "padding_bottom": 28
      }
    }
  },
  "order": [
    "main",
    "features_carousel_RgGmn3",
    "brand_section_bJpXhd",
    "multicolumn",
    "related-products"
  ]
}
